elementstx/__init__.py
elementstx/blech32.py
elementstx/liquid_addr.py
elementstx/py.typed
elementstx/util.py
elementstx/version.py
elementstx/wallet.py
elementstx/core/__init__.py
elementstx/core/script.py
elementstx/core/secp256k1.py
elementstx/tests/__init__.py
elementstx/tests/test_confidential_address.py
elementstx/tests/test_elements_sidechain_transactions.py
elementstx/tests/test_wallet.py
python_elementstx-0.1.5.post0.dist-info/LICENSE
python_elementstx-0.1.5.post0.dist-info/METADATA
python_elementstx-0.1.5.post0.dist-info/WHEEL
python_elementstx-0.1.5.post0.dist-info/top_level.txt
python_elementstx-0.1.5.post0.dist-info/RECORD
