Metadata-Version: 2.1
Name: python-elementstx
Version: 0.1.5.post0
Summary: Elements module for python-bitcointx
Home-page: https://github.com/Simplexum/python-elementstx
Keywords: bitcoin,elements
Classifier: Programming Language :: Python :: 3.7
Classifier: Programming Language :: Python :: 3.8
Classifier: Programming Language :: Python :: 3.9
Classifier: Programming Language :: Python :: 3.10
Classifier: Programming Language :: Python :: 3.11
Classifier: License :: OSI Approved :: GNU Lesser General Public License v3 or later (LGPLv3+)
Requires-Python: >=3.7
License-File: LICENSE
Requires-Dist: python-bitcointx <2,>=1.1.5
